image_duplicate_finder/__init__.py
image_duplicate_finder/__main__.py
image_duplicate_finder/constants.py
image_duplicate_finder/duplication_functions.py
image_duplicate_finder/os_functions.py
image_duplicate_finder/test/__init__.py
image_duplicate_finder/test/test.py
ImageDuplicateFinder-0.6.0.dist-info/LICENSE
ImageDuplicateFinder-0.6.0.dist-info/METADATA
ImageDuplicateFinder-0.6.0.dist-info/WHEEL
ImageDuplicateFinder-0.6.0.dist-info/entry_points.txt
ImageDuplicateFinder-0.6.0.dist-info/top_level.txt
ImageDuplicateFinder-0.6.0.dist-info/RECORD
