Metadata-Version: 2.1
Name: ImageDuplicateFinder
Version: 0.6.0
Summary: Simple duplication finder for Images, matches on names and then compares image hashes.
Home-page: http://pypi.python.org/pypi/picture_duplicate_finder/
Author: Michael Hermelschmidt
Author-email: Michael Hermelschmidt <mail.hermel@gmail.com>
License: Copyright (c) 2022 Michael Hermelschmidt         
Project-URL: Homepage, https://github.com/zeronyk/image_duplication
Keywords: image,duplicates,duplicate-images,deletion,imagehash,remover,duplication-detection
Classifier: License :: OSI Approved :: MIT License
Classifier: Programming Language :: Python
Classifier: Programming Language :: Python :: 3
Requires-Python: >=3.8
License-File: LICENSE
Requires-Dist: ImageHash (>=4.2.1)
